AUTHORS
CONTRIBUTING
envzy/__init__.py
envzy/auto.py
envzy/base.py
envzy/classify.py
envzy/exceptions.py
envzy/packages.py
envzy/py.typed
envzy/pypi.py
envzy/search.py
envzy/spec.py
envzy/utils.py
envzy/version.py
envzy-0.3.0.dist-info/AUTHORS
envzy-0.3.0.dist-info/LICENSE
envzy-0.3.0.dist-info/METADATA
envzy-0.3.0.dist-info/WHEEL
envzy-0.3.0.dist-info/RECORD
