Metadata-Version: 2.1
Name: envzy
Version: 0.3.0
Summary: A library that explores dependencies from a given module or namespace in a local Python environment, then classifies these dependencies.
Home-page: https://github.com/lambdazy/envzy
License: Apache-2.0
Author: Vladimir Lipkin
Author-email: lipkin@yandex-team.ru
Requires-Python: >=3.8,<4.0
Classifier: License :: OSI Approved :: Apache Software License
Classifier: Programming Language :: Python :: 3
Classifier: Programming Language :: Python :: 3.8
Classifier: Programming Language :: Python :: 3.9
Classifier: Programming Language :: Python :: 3.10
Classifier: Programming Language :: Python :: 3.11
Classifier: Programming Language :: Python :: 3.12
Provides-Extra: tests
Requires-Dist: importlib-metadata (>=6.8.0,<7.0.0)
Requires-Dist: packaging (>=23.2,<24.0)
Requires-Dist: pypi-simple (>=1.2.0,<2.0.0)
Requires-Dist: requests (>=2.31.0,<3.0.0)
Requires-Dist: stdlib-list (>=0.9.0,<0.10.0) ; python_version < "3.10"
Requires-Dist: types-pyyaml (>=6.0.12.12,<7.0.0.0) ; extra == "tests"
Requires-Dist: types-requests (>=2.31.0.10,<3.0.0.0) ; extra == "tests"
Requires-Dist: types-setuptools (>=68.2.0.0,<69.0.0.0) ; extra == "tests"
Requires-Dist: types-stdlib-list (>=0.8.3.4,<0.9.0.0) ; extra == "tests"
Requires-Dist: typing-extensions (>=4.8.0,<5.0.0)
Project-URL: Repository, https://github.com/lambdazy/envzy
